microvenv/__init__.py
microvenv/__init__.pyi
microvenv/__main__.py
microvenv/_create.py
microvenv/_create.pyi
microvenv/py.typed
microvenv-2023.4.dist-info/METADATA
microvenv-2023.4.dist-info/WHEEL
microvenv-2023.4.dist-info/licenses/LICENSE
microvenv-2023.4.dist-info/RECORD
