Metadata-Version: 2.1
Name: microvenv
Version: 2023.4
Summary: A minimal re-implementation of Python's venv module plus utilities
Project-URL: Documentation, https://microvenv.readthedocs.io/
Project-URL: Changelog, https://github.com/brettcannon/microvenv/releases
Project-URL: Source, https://github.com/brettcannon/microvenv
Author-email: Brett Cannon <brett@python.org>
Maintainer-email: Brett Cannon <brett@python.org>
License: MIT License
License-File: LICENSE
Keywords: venv,virtual environments
Classifier: Development Status :: 4 - Beta
Classifier: Intended Audience :: Developers
Classifier: License :: OSI Approved :: MIT License
Classifier: Natural Language :: English
Classifier: Topic :: Software Development
Classifier: Topic :: Utilities
Requires-Python: >=3.7
Provides-Extra: doc
Requires-Dist: sphinx; extra == 'doc'
Requires-Dist: sphinx-rtd-theme; extra == 'doc'
Provides-Extra: lint
Requires-Dist: black; extra == 'lint'
Requires-Dist: mypy; extra == 'lint'
Requires-Dist: ruff; extra == 'lint'
Provides-Extra: test
Requires-Dist: pytest; extra == 'test'
